<?xml version="1.0" encoding="UTF-8"?>

<map>
    <name>Wilted Forest</name>
    <icon></icon>
    <tileData>
        <row id="0">
            <column id="0">
                <tile id="0" tileID="0"/>
            </column>
            <column id="1">
                <tile id="0" tileID="0"/>
            </column>
            <column id="2">
                <tile id="0" tileID="0"/>
            </column>
        </row>
        <row id="1">
            <column id="0">
                <tile id="0" tileID="0"/>
            </column>
            <column id="1">
                <tile id="0" tileID="0"/>
            </column>
            <column id="2">
                <tile id="0" tileID="0"/>
            </column>
        </row>
        <row id="2">
            <column id="0">
                <tile id="0" tileID="0"/>
            </column>
            <column id="1">
                <tile id="0" tileID="0"/>
            </column>
            <column id="2">
                <tile id="0" tileID="0"/>
            </column>
        </row>
    </tileData>
</map>
